setup.py
cantrips/__init__.py
cantrips/watch/__init__.py
cantrips/watch/expression.py
cantrips/watch/scope.py
cantrips/watch/undefined.py
python_watch_cantrips.egg-info/PKG-INFO
python_watch_cantrips.egg-info/SOURCES.txt
python_watch_cantrips.egg-info/dependency_links.txt
python_watch_cantrips.egg-info/namespace_packages.txt
python_watch_cantrips.egg-info/requires.txt
python_watch_cantrips.egg-info/top_level.txt