Metadata-Version: 1.0
Name: python-watch-cantrips
Version: 0.0.1
Summary: Python watch cantrips. This will behave as AngularJS's cantrips
Home-page: https://github.com/luismasuelli/python-watch-cantrips
Author: Luis y Anita
Author-email: luismasuelli@hotmail.com
License: LGPL
Platform: UNKNOWN
